test_auth/__init__.py
test_auth/defaults.py
test_auth/utilities.py
test_auth/oidc/__init__.py
test_auth/oidc/templates/home.html
test_auth/openid/__init__.py
test_auth/openid/templates/home.html
test_auth/templates/main.html
test_auth/templates/root.html
fedora_test_auth-0.0.2.dist-info/LICENSE
fedora_test_auth-0.0.2.dist-info/METADATA
fedora_test_auth-0.0.2.dist-info/WHEEL
fedora_test_auth-0.0.2.dist-info/top_level.txt
fedora_test_auth-0.0.2.dist-info/RECORD
