Metadata-Version: 2.1
Name: fedora-test-auth
Version: 0.0.2
Summary: A very basic app to test authentication
Home-page: https://github.com/abompard/test-auth
Author: Aurélien Bompard
Author-email: abompard@fedoraproject.org
Classifier: Programming Language :: Python :: 3
Classifier: License :: OSI Approved :: GNU General Public License v3 or later (GPLv3+)
Classifier: Operating System :: OS Independent
Requires-Python: >=3.6
License-File: LICENSE
Requires-Dist: flask
Requires-Dist: flask-openid
Requires-Dist: python-openid-cla
Requires-Dist: python-openid-teams
Requires-Dist: authlib
